tumorimagingbench/__init__.py
tumorimagingbench/evaluation/RIDER_feature_extractor.py
tumorimagingbench/evaluation/__init__.py
tumorimagingbench/evaluation/base_feature_extractor.py
tumorimagingbench/evaluation/c4c_kits_feature_extractor.py
tumorimagingbench/evaluation/colorectal_feature_extractor.py
tumorimagingbench/evaluation/dlcs_feature_extractor.py
tumorimagingbench/evaluation/extract_all.sh
tumorimagingbench/evaluation/lndb_feature_extractor.py
tumorimagingbench/evaluation/luna_feature_extractor.py
tumorimagingbench/evaluation/nsclc_radiogenomics_feature_extractor.py
tumorimagingbench/evaluation/nsclc_radiomics_feature_extractor.py
tumorimagingbench/evaluation/stability_nsclc_radiomics_feature_extractor.py
tumorimagingbench/evaluation/features/__init__.py
tumorimagingbench/evaluation/features_old/__init__.py
tumorimagingbench/evaluation/readii_eval/__init__.py
tumorimagingbench/evaluation/readii_eval/negative_control_randomized_sampled_non_roi.csv
tumorimagingbench/evaluation/readii_eval/negative_control_randomized_sampled_roi.csv
tumorimagingbench/evaluation/readii_eval/negative_control_shuffled_non_roi.csv
tumorimagingbench/evaluation/readii_eval/negative_control_shuffled_roi.csv
tumorimagingbench/evaluation/readii_eval/original.csv
tumorimagingbench/evaluation/readii_eval/save_nsclc_radiomics_negative_controls.py
tumorimagingbench/evaluation/readii_eval/save_original_features.py
tumorimagingbench/models/__init__.py
tumorimagingbench/models/base.py
tumorimagingbench/models/ct_clip_vit.py
tumorimagingbench/models/ct_fm.py
tumorimagingbench/models/fmcib.py
tumorimagingbench/models/medimageinsight.py
tumorimagingbench/models/medimageinsightmodel.py
tumorimagingbench/models/merlin.py
tumorimagingbench/models/modelsgen.py
tumorimagingbench/models/pasta.py
tumorimagingbench/models/pyramid_extractor.py
tumorimagingbench/models/suprem.py
tumorimagingbench/models/unet3d.py
tumorimagingbench/models/utils.py
tumorimagingbench/models/vista3d.py
tumorimagingbench-0.1.3.dist-info/METADATA
tumorimagingbench-0.1.3.dist-info/WHEEL
tumorimagingbench-0.1.3.dist-info/RECORD
