Metadata-Version: 2.4
Name: tumorimagingbench
Version: 0.1.3
Summary: A package for tumor imaging feature extraction and benchmarking.
Author-email: Suraj Pai <bspai@bwh.harvard.edu>
Requires-Python: <3.13,>=3.10
Requires-Dist: foundation-cancer-image-biomarker
Requires-Dist: huggingface-hub
Requires-Dist: itk
Requires-Dist: merlin-vlm
Requires-Dist: multiprocess
Requires-Dist: numpy
Requires-Dist: pandas<2.0.0,>=1.5.3
Requires-Dist: scikit-learn
Requires-Dist: torch
Requires-Dist: transformers
